newrelic_python_agent/__init__.py
newrelic_python_agent/agent.py
newrelic_python_agent/plugins/__init__.py
newrelic_python_agent/plugins/apache_httpd.py
newrelic_python_agent/plugins/base.py
newrelic_python_agent/plugins/couchdb.py
newrelic_python_agent/plugins/elasticsearch.py
newrelic_python_agent/plugins/haproxy.py
newrelic_python_agent/plugins/memcached.py
newrelic_python_agent/plugins/mongodb.py
newrelic_python_agent/plugins/mysql-config.py
newrelic_python_agent/plugins/mysql.py
newrelic_python_agent/plugins/nginx.py
newrelic_python_agent/plugins/pgbouncer.py
newrelic_python_agent/plugins/php_apc.py
newrelic_python_agent/plugins/php_fpm.py
newrelic_python_agent/plugins/postgresql.py
newrelic_python_agent/plugins/prometheus.py
newrelic_python_agent/plugins/rabbitmq.py
newrelic_python_agent/plugins/redis.py
newrelic_python_agent/plugins/riak.py
newrelic_python_agent/plugins/uwsgi.py
opt/newrelic-python-agent/LICENSE
opt/newrelic-python-agent/README.rst
opt/newrelic-python-agent/apc-nrp.php
opt/newrelic-python-agent/newrelic-python-agent.cfg
opt/newrelic-python-agent/newrelic-python-agent.deb
opt/newrelic-python-agent/newrelic-python-agent.rhel
newrelic_python_agent-1.4.0.dist-info/LICENSE
newrelic_python_agent-1.4.0.dist-info/METADATA
newrelic_python_agent-1.4.0.dist-info/WHEEL
newrelic_python_agent-1.4.0.dist-info/entry_points.txt
newrelic_python_agent-1.4.0.dist-info/top_level.txt
newrelic_python_agent-1.4.0.dist-info/RECORD
